setup.py
Localize_M.egg-info/PKG-INFO
Localize_M.egg-info/SOURCES.txt
Localize_M.egg-info/dependency_links.txt
Localize_M.egg-info/entry_points.txt
Localize_M.egg-info/requires.txt
Localize_M.egg-info/top_level.txt
localize_m/__init__.py
localize_m/main.py