Metadata-Version: 1.1
Name: Localize-M
Version: 1.0.1
Summary: Localize objc M files
Home-page: https://github.com/jrtaal/localize_m
Author: Jacco Taal
Author-email: jacco@bitnomica.com
License: LICENSE.txt
Platform: UNKNOWN
Classifier: Development Status :: 4 - Beta
Classifier: Topic :: Utilities
